Workbook

Sheet Dell's Complete Financials
A1: Financial Statement for: DELL TECHNOLOGIES INC
A2: Fiscal Years: 2024 to 2024
A3: Numbers in millions USD | B3: 2024 | F3: Download and Copy Dell's latest Complete Financial Statements from the WRDS into this sheet
A5: BALANCE SHEET
A6: ASSETS
A7: Cash and Short-Term Investments | B7: 3756
A8: Cash | B8: 3633
A9: Short-Term Investments | B9: 123
A10: Receivables | B10: 15602
A11: Receivables - Trade | B11: 15602
A12: Income Tax Refund | B12: 0
A13: Current Receivables - Other | B13: 0
A14: Inventories - Total | B14: 6716
A15: Inventories - Raw Materials | B15: 4432
A16: Inventories - Work in Process | B16: 1128
A17: Inventories - Finished Goods | B17: 1156
A18: Inventories - Other | B18: 0
... A29: Assets - Other | B29: 4367
A30: Deferred Charges | B30: .
A31: Other Asst., Excl.Def.Chg. | B31: 4367
A32: Assets - Total | B32: 79746
A33: LIABILITIES
A34: Debt in Current Liabilities | B34: 5440
A35: Notes Payable | B35: 0
A36: Debt - Due in One Year | B36: 5440
A37: Accounts Payable | B37: 20832
A38: Income Taxes Payable | B38: .
A39: Current Liabilities - Other | B39: 20255
A40: Accrued Expense | B40: .
A41: Other Curr.Liab., Excl.Accr.Exp. | B41: 20255
A42: Current Liabilities - Total | B42: 46527
A43: Long-Term Debt - Total | B43: 19885
A44: Debt - Convertible (Total) | B44: 0
A45: Debt - Subordinated Convertible | B45: 0
A46: Debt - Senior Convertible | B46: 0
A47: Debt - Subordinated | B47: 0
A48: Debt - Notes | B48: 16025
A49: Debt - Debentures | B49: .
A50: Long-Term Debt - Other | B50: 9521
A51: Debt - Cap. Lease Oblig. | B51: 0
A52: Liabilities - Other | B52: 14721
A53: Def. Taxes and Invest.Tax Cred. | B53: .
A54: Deferred Taxes | B54: .
A55: Investment Tax Credit | B55: 0
A56: Noncontrolling Interest - Redeemable | B56: 0
A57: Liabilities - Total | B57: .
A58: SHAREHOLDERS' EQUITY
A59: Preferred Stock - Carrying Value | B59: 0
A60: Pref. Stock - Redeemable | B60: 0
A61: Pref. Stock - Nonredeemable | B61: 0
A62: Common Equity - Total | B62: -1482
A63: Common Stock | B63: 8
A64: Capital Surplus | B64: 9111
A65: Retained Earnings | B65: -2099
A66: Less: Treas.Stock - Total $ Amt. | B66: 8502
A67: Shareholders Equity - Parent | B67: -1482
A68: Noncontrolling Interest - Nonredeemable | B68: 95
A69: Shareholders Equity - Total | B69: -1387
A70: Total Liabilities and Shareholders Equity | B70: 79746
A72: INCOME STATEMENT
A73: Sales (Net) | B73: 95567
A74: Cost of Goods Sold | B74: 71468
A75: Selling, General, and Administrative Expense | B75: 14046
A76: Operating Income Before Depreciation | B76: 10053
A77: Depreciation and Amortization | B77: 3123
A78: Amortization of Intangibles | B78: 992
A79: Depreciation Expense (Schedule VI) | B79: .
A80: Depletion Expense (Schedule VI) | B80: .
A81: Operating Income After Depreciation | B81: 6930
A82: Interest Expense | B82: 1394
A83: Nonoperating Income (Expense) | B83: 205
A84: Nonoperating Income (Expense) - Excluding Interest Income | B84: 205
A85: Interest Income | B85: .
A86: Special Items | B86: -693
A87: Pretax Income | B87: 5048
A88: Pretax Income - Domestic | B88: -73
A89: Pretax Income - Foreign | B89: 5121
A90: Income Taxes - Total | B90: 472
A91: Deferred Taxes (Income Account) | B91: -208
A92: Deferred Taxes - Federal | B92: -220
A93: Deferred Taxes - Foreign | B93: 24
A94: Deferred Taxes - State | B94: -12
A95: Income Taxes - Federal | B95: -84
A96: Income Taxes - Foreign | B96: 785
A97: Income Taxes - State | B97: -21
... A109: Net Income (Loss) | B109: 4592
A111: STATEMENT OF CASH FLOWS
A112: INDIRECT OPERATING ACTIVITIES
A113: Income Before Extraordinary Items | B113: 4576
A114: Depreciation and Amortization | B114: 3123
A115: Extraordinary Items and Discontinued Operations | B115: 0
A116: Deferred Taxes | B116: -208
A117: Equity in Net Loss (Earnings) | B117: 0
A118: Sale of Property, Plant, and Equipment and Sale of Investments - Loss (Gain) | B118: 0
A119: Funds from Operations - Other | B119: 1238
A120: Accounts Receivable - Decrease (Increase) | B120: -2246
A121: Inventory - Decrease (Increase) | B121: -3515
A122: Accounts Payable and Accrued Liabilities - Increase (Decrease) | B122: 1703
A123: Income Taxes - Accrued - Increase (Decrease) | B123: .
A124: Assets and Liablities - Other (Net Change) | B124: -150
...

Sheet Dell's cost of capital
A1: Step 1
A2: i | B2: risk free rate (5-year Treasury Yield) | C2: 0.03719 | D2: Refer to the instruction
A3: ii | B3: equity beta | C3: 1.09 | D3: Refer to the instruction
A4: iii | B4: expected market risk premium | C4: 0.04
B5: cost of equity rE | C5: =C2+C3*C4 -> 0.08079 | D5: Note that rE = risk free rate + equity beta * expected market risk premium, NOT risk free rate + equity beta * (expected market risk premium - risk free rate)
A7: Step 2 | B7: S&P's Credit Rating (if available) | C7: BBB
B8: debt beta | C8: 0.1
B9: cost of debt rD | C9: =C2+C8*C4 -> 0.04119 | D9: rD = risk free rate + debt beta * expected market risk premium
A11: Step 3.1 | C11: Latest Fiscal Year
B12: Cash and Short-Term Investments | C12: ='Dell''s Complete Financials'!B7 -> 3756 | D12: USD million
B13: Debt in Current Liabilities | C13: ='Dell''s Complete Financials'!B34 -> 5440 | D13: USD million
B14: Long-Term Debt - Total | C14: ='Dell''s Complete Financials'!B43 -> 19885 | D14: USD million
B15: Net Debt | C15: =C13+C14-C12 -> 21569 | D15: USD million | E15: "Debt in Current Liabilities" + "Long-Term Debt - Total" - "Cash and Short-Term Investments"
A17: Step 3.2 | B17: Stock Price | C17: 103.6 | D17: USD | E17: Refer to the instruction
B18: Shares Outstanding | C18: ='Dell''s Complete Financials'!B313 -> 696 | D18: millions | E18: The variable "SHARES - Outstanding at Fiscal Year End" reported in the WRDS is in the unit of millions.
B19: Market Value of Equity | C19: =C17*C18 -> 72105.6 | D19: USD million | E19: Stock price * Shares Outstanding
A20: Step 3.3 | B20: Enterprise Value | C20: =C19+C15 -> 93674.6 | D20: USD million | E20: MV Equity + Net Debt
A22: Step 4 | B22: Tax rate | C22: 0.21
B23: WACC | C23: =C19/C20*C5+C15/C20*C9*(1-C22) -> 0.069680242

Sheet Your Company's Financials
A1: Financial Statement for: MICROSOFT CORP
A2: Fiscal Years: 2018 to 2024
E3: 2024 | F3: Download and Copy the latest Complete Financial Statements for your company from the WRDS into this sheet
A5: BALANCE SHEET
A6: ASSETS
A7: Cash and Short-Term Investments | E7: 75543
A8: Cash | E8: 18315
A9: Short-Term Investments | E9: 57228
A10: Receivables | E10: 67424
A11: Receivables - Trade | E11: 56924
A12: Income Tax Refund | E12: 0
A13: Current Receivables - Other | E13: 10500
A14: Inventories - Total | E14: 1246
A15: Inventories - Raw Materials | E15: 394
A16: Inventories - Work in Process | E16: 7
A17: Inventories - Finished Goods | E17: 845
A18: Inventories - Other | E18: 0
... A32: Assets - Total | E32: 512163
A33: LIABILITIES
A34: Debt in Current Liabilities | E34: 14871
A35: Notes Payable | E35: 6693
A36: Debt - Due in One Year | E36: 8178
A37: Accounts Payable | E37: 21996
A38: Income Taxes Payable | E38: 5017
A39: Current Liabilities - Other | E39: 83402
A40: Accrued Expense | E40: 12564
A41: Other Curr.Liab., Excl.Accr.Exp. | E41: 70838
A42: Current Liabilities - Total | E42: 125286
A43: Long-Term Debt - Total | E43: 82981
A44: Debt - Convertible (Total) | E44: 0
A45: Debt - Subordinated Convertible | E45: 0
... A57: Liabilities - Total | E57: 243686
A58: SHAREHOLDERS' EQUITY
A59: Preferred Stock - Carrying Value | E59: 0
A60: Pref. Stock - Redeemable | E60: 0
A61: Pref. Stock - Nonredeemable | E61: 0
A62: Common Equity - Total | E62: 268477
A63: Common Stock | E63: 0.046
A64: Capital Surplus | E64: 100922.95
A65: Retained Earnings | E65: 167554
A66: Less: Treas.Stock - Total $ Amt. | E66: 0
A67: Shareholders Equity - Parent | E67: 268477
A68: Noncontrolling Interest - Nonredeemable | E68: 0
A69: Shareholders Equity - Total | E69: 268477
A70: Total Liabilities and Shareholders Equity | E70: 512163
A72: INCOME STATEMENT
A73: Sales (Net) | E73: 245122
A74: Cost of Goods Sold | E74: 54114
A75: Selling, General, and Administrative Expense | E75: 61575
A76: Operating Income Before Depreciation | E76: 129433
A77: Depreciation and Amortization | E77: 20000
A78: Amortization of Intangibles | E78: 4800
A79: Depreciation Expense (Schedule VI) | E79: .
A80: Depletion Expense (Schedule VI) | E80: .
A81: Operating Income After Depreciation | E81: 109433
A82: Interest Expense | E82: 2983
A83: Nonoperating Income (Expense) | E83: 1337
A84: Nonoperating Income (Expense) - Excluding Interest Income | E84: 1337
A85: Interest Income | E85: .
A86: Special Items | E86: 0
A87: Pretax Income | E87: 107787
A88: Pretax Income - Domestic | E88: 62886
A89: Pretax Income - Foreign | E89: 44901
A90: Income Taxes - Total | E90: 19651
A91: Deferred Taxes (Income Account) | E91: -4738
A92: Deferred Taxes - Federal | E92: -4791
A93: Deferred Taxes - Foreign | E93: 432
A94: Deferred Taxes - State | E94: -379
A95: Income Taxes - Federal | E95: 12165
A96: Income Taxes - Foreign | E96: 9858
A97: Income Taxes - State | E97: 2366
... A109: Net Income (Loss) | E109: 88136
A111: STATEMENT OF CASH FLOWS
A112: INDIRECT OPERATING ACTIVITIES
A113: Income Before Extraordinary Items | E113: 88136
A114: Depreciation and Amortization | E114: 22287
A115: Extraordinary Items and Discontinued Operations | E115: 0
A116: Deferred Taxes | E116: -4738
A117: Equity in Net Loss (Earnings) | E117: .
A118: Sale of Property, Plant, and Equipment and Sale of Investments - Loss (Gain) | E118: .
A119: Funds from Operations - Other | E119: 11039
A120: Accounts Receivable - Decrease (Increase) | E120: -7191
A121: Inventory - Decrease (Increase) | E121: 1284
A122: Accounts Payable and Accrued Liabilities - Increase (Decrease) | E122: 3545
A123: Income Taxes - Accrued - Increase (Decrease) | E123: .
A124: Assets and Liablities - Other (Net Change) | E124: 4186
A125: Operating Activities - Net Cash Flow | E125: 118548
A126: INVESTING ACTIVITIES
A127: Increase in Investments | E127: 17732
A128: Sale of Investments | E128: 35669
A129: Short-Term Investments - Change | E129: .
A130: Capital Expenditures | E130: 44477
A131: Sale of Property, Plant, and Equipment | E131: 0
A132: Acquisitions | E132: .
A133: Investing Activities - Other | E133: -70430
A134: Investing Activities - Net Cash Flow | E134: -96970
A135: FINANCING ACTIVITIES
A136: Sale of Common and Preferred Stock | E136: 2002
A137: Purchase of Common and Preferred Stock | E137: 17254
A138: Cash Dividends | E138: 21771
...

Sheet Your Company's Cost of Capital
A1: Step 1
A2: i | B2: risk free rate (5-year Treasury Yield) | C2: ='Dell''s cost of capital'!C2 -> 0.03719
A3: ii | B3: equity beta | C3: 1.07
A4: iii | B4: expected market risk premium | C4: 0.04
B5: cost of equity rE | C5: =C2+C3*C4 -> 0.07999
A7: Step 2 | B7: S&P's Credit Rating (if available) | C7: AAA
B8: debt beta | C8: 0.05
B9: cost of debt rD | C9: =C2+C8*C4 -> 0.03919
F10: Notes of considertion for additional self analysis
A11: Step 3.1 | C11: Latest Fiscal Year | F11: MV_Debt (Book) | H11: E% Weight | J11: D% Weight | L11: Total Firm Value | N11: E% & D% WACC
B12: Cash and Short-Term Investments | C12: ='Your Company''s Financials'!E7 -> 75543 | D12: USD million | F12: =C13+C14 -> 97852 | H12: =C19/L12 -> 0.96926187 | J12: =F12/L12 -> 0.030738127 | L12: =C19+F12 -> 3183408 | N12: =H12*C5+J12*C9*(1-C22) -> 0.078398589
B13: Debt in Current Liabilities | C13: ='Your Company''s Financials'!E34 -> 14871 | D13: USD million
B14: Long-Term Debt - Total | C14: ='Your Company''s Financials'!E43 -> 82981 | D14: USD million | F14: Book Debt proxied for MV of Debt | J14: D/E Ratio | L14: Net D/E Ratio
B15: Net Debt | C15: =C13+C14-C12 -> 22309 | D15: USD million | F15: Net Debt = Book Debt- Cash | J15: =F12/C19 -> 0.031712923 | L15: =C15/C19 -> 0.0072301393
A17: Step 3.2 | B17: Stock Price | C17: 415.06 | D17: USD
B18: Shares Outstanding | C18: ='Your Company''s Financials'!E313 -> 7434 | D18: millions | E18: The variable "SHARES - Outstanding at Fiscal Year End" reported in the WRDS is in the unit of millions.
B19: Market Value of Equity | C19: =C18*C17 -> 3085556 | D19: USD million
A20: Step 3.3 | B20: Enterprise Value | C20: =C19+C15 -> 3107865 | D20: USD million | F20: EV= MV Equity + Net Debt
A22: Step 4 | B22: Tax rate | C22: 0.28
B23: WACC | C23: =(C19/C20)*C5+(C15/C20)*C9*(1-C22) -> 0.07961836 | F23: *Net Debt WACC

Sheet Update Q6 in Case Part I.2
A1: NPV for Your Company's Project
A3: Assumptions (Amounts in Millions Unless Otherwise Indicated)
A4: Initial Capital Expenditure (Year 0) | B4: 14000 | C4: <-- Simply apply the same assumptions for all parameters as you did in Case Part I.2 for your company. The only parameter you need to update is the cost of capital. You should use your estimated cost of capital for your company (cell C23 from the sheet "Your Company's Cost of Capital") to update your DCF analysis.
A5: Useful Life of Assets (in year) | B5: 5
A6: Annual Depreciation | B6: =B4/B5 -> 2800
A7: EBITDA/Sales profit margin | B7: ='[1]Your Company''s FS'!L21 -> 0.52803502
A8: Net working capital in the last year | B8: ='[1]Your Company''s FS'!L35 -> 46674
A9: Net working capital/Sales (Net) in the last year | B9: ='[1]Your Company''s FS'!L35/'[1]Your Company''s FS'!L11 -> 0.19041131
A10: Initial Net Working Capital (Year 0) | B10: =0.01*C19 -> 147.0732
A11: Net Working Capital in Year 5 | B11: 0
A12: Tax Rate | B12: 0.21
A13: Cost of Capital | B13: ='Your Company''s Cost of Capital'!C23 -> 0.07961836 | C13: <-- Use your estimate of the cost of capital for your company here. The final NPV should update automatically if you use cell reference correctly and never hardcoded
A14: Revenues in Year 1 | B14: =0.06*'[1]Your Company''s FS'!L11 -> 14707.32
A15: Revenue Growth Rate per Year | C15: 0.06 | D15: 0.15 | E15: 0.14 | F15: 0.1 | G15: 0.06
B16: Year | C16: Year | D16: Year | E16: Year | F16: Year | G16: Year
B17: 2025 | C17: =B17+1 -> 2026 | D17: =C17+1 -> 2027 | E17: =D17+1 -> 2028 | F17: =E17+1 -> 2029 | G17: =F17+1 -> 2030
A18: Unlevered Income Statements | B18: 0 | C18: 1 | D18: 2 | E18: 3 | F18: 4 | G18: 5
A19: Revenues | C19: =B14 -> 14707.32 | D19: =C19*(1+D15) -> 16913.418 | E19: =D19*(1+E15) -> 19281.297 | F19: =E19*(1+F15) -> 21209.426 | G19: =F19*(1+G15) -> 22481.992
A20: EBITDA | C20: =C19*$B$7 -> 7765.98 | D20: =D19*$B$7 -> 8930.877 | E20: =E19*$B$7 -> 10181.2 | F20: =F19*$B$7 -> 11199.32 | G20: =G19*$B$7 -> 11871.279
A21: Depreciation | C21: =B6 -> 2800 | D21: =C21 -> 2800 | E21: =D21 -> 2800 | F21: =E21 -> 2800 | G21: =F21 -> 2800
A22: Tax | C22: =(C20-C21)*$B$12 -> 1042.8558 | D22: =(D20-D21)*$B$12 -> 1287.4842 | E22: =(E20-E21)*$B$12 -> 1550.052 | F22: =(F20-F21)*$B$12 -> 1763.8571 | G22: =(G20-G21)*$B$12 -> 1904.9686
A23: Unlevered Net Income | C23: =(C20-C21)*(1-$B$12) -> 3923.1242 | D23: =(D20-D21)*(1-$B$12) -> 4843.3928 | E23: =(E20-E21)*(1-$B$12) -> 5831.1478 | F23: =(F20-F21)*(1-$B$12) -> 6635.4626 | G23: =(G20-G21)*(1-$B$12) -> 7166.3104
A25: Working Capital Calculations
A26: NWC Level | B26: =B10 -> 147.0732 | C26: =C19*$B$9 -> 2800.44 | D26: =D19*$B$9 -> 3220.506 | E26: =E19*$B$9 -> 3671.3768 | F26: =F19*$B$9 -> 4038.5145 | G26: 0
A27: Change in NWC | C27: =C26-B26 -> 2653.3668 | D27: =D26-C26 -> 420.066 | E27: =E26-D26 -> 450.87084 | F27: =F26-E26 -> 367.13768 | G27: =G26-F26 -> -4038.5145
A28: CF from Change in NWC | C28: =-C27 -> -2653.3668 | D28: =-D27 -> -420.066 | E28: =-E27 -> -450.87084 | F28: =-F27 -> -367.13768 | G28: =-G27 -> 4038.5145
A30: Calculating Free Cash Flows
A31: Unlevered Net Income | C31: =(C20-C21)*(1-$B$12) -> 3923.1242 | D31: =(D20-D21)*(1-$B$12) -> 4843.3928 | E31: =(E20-E21)*(1-$B$12) -> 5831.1478 | F31: =(F20-F21)*(1-$B$12) -> 6635.4626 | G31: =(G20-G21)*(1-$B$12) -> 7166.3104
A32: Add Back Depreciation | C32: =C21 -> 2800 | D32: =D21 -> 2800 | E32: =E21 -> 2800 | F32: =F21 -> 2800 | G32: =G21 -> 2800
A33: Subtract Change in NWC | C33: =C27 -> 2653.3668 | D33: =D27 -> 420.066 | E33: =E27 -> 450.87084 | F33: =F27 -> 367.13768 | G33: =G27 -> -4038.5145
A34: Subtract Capital Expenditure | B34: =B4 -> 14000 | C34: 0 | D34: 0 | E34: 0 | F34: 0 | G34: 0
A35: Free Cash Flow | B35: =-(B34+B26) -> -14147.073 | C35: =C31+C32-C33-C34 -> 4069.7574 | D35: =D31+D32-D33-D34 -> 7223.3268 | E35: =E31+E32-E33-E34 -> 8180.277 | F35: =F31+F32-F33-F34 -> 9068.3249 | G35: =G31+G32-G33-G34 -> 14004.825
A37: Discount Factor (1/(1+r)^n) | B37: =(1/(1+$B$13)^B18) -> 1 | C37: =(1/(1+$B$13)^C18) -> 0.92625324 | D37: =(1/(1+$B$13)^D18) -> 0.85794506 | E37: =(1/(1+$B$13)^E18) -> 0.79467439 | F37: =(1/(1+$B$13)^F18) -> 0.73606972 | G37: =(1/(1+$B$13)^G18) -> 0.68178696
A38: PV(FCF) | B38: =B35*B37 -> -14147.073 | C38: =C35*C37 -> 3769.626 | D38: =D35*D37 -> 6197.2176 | E38: =E35*E37 -> 6500.6566 | F38: =F35*F37 -> 6674.9194 | G38: =G35*G37 -> 9548.307
A39: NPV | B39: =B35+NPV(B13,C35,D35,E35,F35,G35) -> 18543.653
